blackspammerbd_webmaster/__init__.py
blackspammerbd_webmaster/admin_finder.py
blackspammerbd_webmaster/brute_forcer.py
blackspammerbd_webmaster/cli.py
blackspammerbd_webmaster/extractor.py
blackspammerbd_webmaster/sql_tester.py
blackspammerbd_webmaster/utils.py
blackspammerbd_webmaster-1.0.0.dist-info/licenses/LICENSE
blackspammerbd_webmaster-1.0.0.dist-info/METADATA
blackspammerbd_webmaster-1.0.0.dist-info/WHEEL
blackspammerbd_webmaster-1.0.0.dist-info/entry_points.txt
blackspammerbd_webmaster-1.0.0.dist-info/top_level.txt
blackspammerbd_webmaster-1.0.0.dist-info/RECORD
