Metadata-Version: 2.4
Name: blackspammerbd-webmaster
Version: 1.0.0
Summary: A powerful and modular web penetration testing toolkit.
Home-page: https://github.com/BlackSpammerBd/blackspammerbd_webmaster
Author: BLACK SPAMMER BD
Author-email: shawponsp6@gmail.com
Project-URL: Source Code, https://github.com/BlackSpammerBd/blackspammerbd_webmaster
Project-URL: Bug Tracker, https://github.com/BlackSpammerBd/blackspammerbd_webmaster/issues
Project-URL: Team, https://facebook.com/original.Typeboss.ur.father
Keywords: pentest blackspammerbd web-security hacking toolkit
Classifier: Development Status :: 5 - Production/Stable
Classifier: Intended Audience :: Developers
Classifier: Topic :: Security
Classifier: Topic :: Software Development :: Build Tools
Classifier: License :: OSI Approved :: MIT License
Classifier: Operating System :: OS Independent
Classifier: Programming Language :: Python :: 3
Classifier: Programming Language :: Python :: 3.6
Classifier: Programming Language :: Python :: 3.7
Classifier: Programming Language :: Python :: 3.8
Classifier: Programming Language :: Python :: 3.9
Requires-Python: >=3.6
License-File: LICENSE
Requires-Dist: requests>=2.20.0
Requires-Dist: beautifulsoup4>=4.9.0
Requires-Dist: colorama>=0.4.3
Dynamic: author
Dynamic: author-email
Dynamic: classifier
Dynamic: description
Dynamic: description-content-type
Dynamic: home-page
Dynamic: keywords
Dynamic: license-file
Dynamic: project-url
Dynamic: requires-dist
Dynamic: requires-python
Dynamic: summary
